<?xml version="1.0"?>
<ArrayOfVertex xmlns:xsi="http://www.w3.org/2001/XMLSchema-instance" xmlns:xsd="http://www.w3.org/2001/XMLSchema">
  <Vertex>
    <x>26</x>
    <y>52</y>
    <Name>0</Name>
  </Vertex>
  <Vertex>
    <x>19</x>
    <y>156</y>
    <Name>0</Name>
  </Vertex>
  <Vertex>
    <x>21</x>
    <y>272</y>
    <Name>0</Name>
  </Vertex>
  <Vertex>
    <x>24</x>
    <y>398</y>
    <Name>0</Name>
  </Vertex>
  <Vertex>
    <x>29</x>
    <y>543</y>
    <Name>0</Name>
  </Vertex>
  <Vertex>
    <x>216</x>
    <y>608</y>
    <Name>1</Name>
  </Vertex>
  <Vertex>
    <x>250</x>
    <y>503</y>
    <Name>0</Name>
  </Vertex>
  <Vertex>
    <x>284</x>
    <y>402</y>
    <Name>0</Name>
  </Vertex>
  <Vertex>
    <x>177</x>
    <y>368</y>
    <Name>0</Name>
  </Vertex>
  <Vertex>
    <x>190</x>
    <y>267</y>
    <Name>0</Name>
  </Vertex>
  <Vertex>
    <x>317</x>
    <y>309</y>
    <Name>0</Name>
  </Vertex>
  <Vertex>
    <x>359</x>
    <y>207</y>
    <Name>0</Name>
  </Vertex>
  <Vertex>
    <x>383</x>
    <y>146</y>
    <Name>0</Name>
  </Vertex>
  <Vertex>
    <x>580</x>
    <y>161</y>
    <Name>0</Name>
  </Vertex>
  <Vertex>
    <x>683</x>
    <y>197</y>
    <Name>0</Name>
  </Vertex>
  <Vertex>
    <x>653</x>
    <y>302</y>
    <Name>0</Name>
  </Vertex>
  <Vertex>
    <x>504</x>
    <y>253</y>
    <Name>0</Name>
  </Vertex>
  <Vertex>
    <x>617</x>
    <y>402</y>
    <Name>0</Name>
  </Vertex>
  <Vertex>
    <x>462</x>
    <y>353</y>
    <Name>0</Name>
  </Vertex>
  <Vertex>
    <x>420</x>
    <y>450</y>
    <Name>0</Name>
  </Vertex>
  <Vertex>
    <x>581</x>
    <y>504</y>
    <Name>0</Name>
  </Vertex>
  <Vertex>
    <x>558</x>
    <y>602</y>
    <Name>0</Name>
  </Vertex>
  <Vertex>
    <x>418</x>
    <y>559</y>
    <Name>0</Name>
  </Vertex>
  <Vertex>
    <x>530</x>
    <y>710</y>
    <Name>0</Name>
  </Vertex>
  <Vertex>
    <x>387</x>
    <y>666</y>
    <Name>0</Name>
  </Vertex>
  <Vertex>
    <x>20</x>
    <y>114</y>
    <Name>0</Name>
  </Vertex>
  <Vertex>
    <x>743</x>
    <y>215</y>
    <Name>0</Name>
  </Vertex>
  <Vertex>
    <x>802</x>
    <y>235</y>
    <Name>0</Name>
  </Vertex>
  <Vertex>
    <x>768</x>
    <y>337</y>
    <Name>0</Name>
  </Vertex>
  <Vertex>
    <x>732</x>
    <y>440</y>
    <Name>0</Name>
  </Vertex>
  <Vertex>
    <x>674</x>
    <y>421</y>
    <Name>0</Name>
  </Vertex>
  <Vertex>
    <x>819</x>
    <y>467</y>
    <Name>0</Name>
  </Vertex>
  <Vertex>
    <x>883</x>
    <y>261</y>
    <Name>0</Name>
  </Vertex>
  <Vertex>
    <x>847</x>
    <y>385</y>
    <Name>0</Name>
  </Vertex>
  <Vertex>
    <x>993</x>
    <y>294</y>
    <Name>0</Name>
  </Vertex>
  <Vertex>
    <x>961</x>
    <y>396</y>
    <Name>0</Name>
  </Vertex>
  <Vertex>
    <x>926</x>
    <y>503</y>
    <Name>0</Name>
  </Vertex>
  <Vertex>
    <x>1100</x>
    <y>333</y>
    <Name>0</Name>
  </Vertex>
  <Vertex>
    <x>1067</x>
    <y>435</y>
    <Name>0</Name>
  </Vertex>
  <Vertex>
    <x>1034</x>
    <y>544</y>
    <Name>0</Name>
  </Vertex>
  <Vertex>
    <x>698</x>
    <y>536</y>
    <Name>0</Name>
  </Vertex>
  <Vertex>
    <x>664</x>
    <y>637</y>
    <Name>0</Name>
  </Vertex>
  <Vertex>
    <x>751</x>
    <y>666</y>
    <Name>0</Name>
  </Vertex>
  <Vertex>
    <x>793</x>
    <y>552</y>
    <Name>0</Name>
  </Vertex>
  <Vertex>
    <x>890</x>
    <y>615</y>
    <Name>0</Name>
  </Vertex>
  <Vertex>
    <x>858</x>
    <y>702</y>
    <Name>0</Name>
  </Vertex>
  <Vertex>
    <x>906</x>
    <y>721</y>
    <Name>0</Name>
  </Vertex>
  <Vertex>
    <x>964</x>
    <y>742</y>
    <Name>0</Name>
  </Vertex>
  <Vertex>
    <x>1000</x>
    <y>643</y>
    <Name>0</Name>
  </Vertex>
  <Vertex>
    <x>1125</x>
    <y>569</y>
    <Name>0</Name>
  </Vertex>
  <Vertex>
    <x>1185</x>
    <y>362</y>
    <Name>0</Name>
  </Vertex>
  <Vertex>
    <x>1155</x>
    <y>472</y>
    <Name>0</Name>
  </Vertex>
  <Vertex>
    <x>1057</x>
    <y>766</y>
    <Name>0</Name>
  </Vertex>
  <Vertex>
    <x>1086</x>
    <y>673</y>
    <Name>0</Name>
  </Vertex>
  <Vertex>
    <x>1223</x>
    <y>602</y>
    <Name>0</Name>
  </Vertex>
  <Vertex>
    <x>1252</x>
    <y>516</y>
    <Name>0</Name>
  </Vertex>
  <Vertex>
    <x>1293</x>
    <y>394</y>
    <Name>0</Name>
  </Vertex>
  <Vertex>
    <x>1406</x>
    <y>433</y>
    <Name>0</Name>
  </Vertex>
  <Vertex>
    <x>1367</x>
    <y>543</y>
    <Name>0</Name>
  </Vertex>
  <Vertex>
    <x>1341</x>
    <y>640</y>
    <Name>0</Name>
  </Vertex>
</ArrayOfVertex>